ZhihuVAPI/__init__.py
ZhihuVAPI/config.py
ZhihuVAPI/test.py
ZhihuVAPI/content/Ancestry.py
ZhihuVAPI/content/Answer.py
ZhihuVAPI/content/Article.py
ZhihuVAPI/content/Collection.py
ZhihuVAPI/content/Column.py
ZhihuVAPI/content/Comment.py
ZhihuVAPI/content/People.py
ZhihuVAPI/content/Pin.py
ZhihuVAPI/content/Question.py
ZhihuVAPI/content/Topic.py
ZhihuVAPI/content/__init__.py
ZhihuVAPI/util/Session.py
ZhihuVAPI/util/__init__.py
ZhihuVAPI/util/urls.py
ZhihuVAPI/util/zhihu.py
ZhihuVAPI-1.0.6.dist-info/LICENSE.txt
ZhihuVAPI-1.0.6.dist-info/METADATA
ZhihuVAPI-1.0.6.dist-info/RECORD
ZhihuVAPI-1.0.6.dist-info/WHEEL
ZhihuVAPI-1.0.6.dist-info/top_level.txt
